jnormcorre/__init__.py
jnormcorre/motion_correction.py
jnormcorre/onephotonmethods.py
jnormcorre/simulation.py
jnormcorre/utils/__init__.py
jnormcorre/utils/lazy_array.py
jnormcorre/utils/registrationarrays.py
jnormcorre-1.0.0.dist-info/METADATA
jnormcorre-1.0.0.dist-info/WHEEL
jnormcorre-1.0.0.dist-info/top_level.txt
jnormcorre-1.0.0.dist-info/RECORD
