Metadata-Version: 2.1
Name: jnormcorre
Version: 1.0.0
Summary: Jax-accelerated implementation of normcorre
Classifier: Programming Language :: Python :: 3
Requires-Dist: future
Requires-Dist: numpy
Requires-Dist: scipy
Requires-Dist: h5py
Requires-Dist: tqdm
Requires-Dist: matplotlib
Requires-Dist: opencv-python
Requires-Dist: tifffile
Requires-Dist: typing
Requires-Dist: torch
Requires-Dist: pynwb
Requires-Dist: pillow
Requires-Dist: scikit-image
Requires-Dist: jax
Requires-Dist: jaxlib
Requires-Dist: pytest
